datasette_jsonschema_forms/__init__.py
datasette_jsonschema_forms/contract.py
datasette_jsonschema_forms/internal_db.py
datasette_jsonschema_forms/internal_migrations.py
datasette_jsonschema_forms/routes.py
datasette_jsonschema_forms/static/form.min.js
datasette_jsonschema_forms/static/index.min.js
datasette_jsonschema_forms/static/new.min.css
datasette_jsonschema_forms/static/new.min.js
datasette_jsonschema_forms/templates/jsonschema-forms-base.html
datasette_jsonschema_forms-0.0.3.dist-info/licenses/LICENSE
scripts/pydantic-to-jsonschema.py
tests/test_jsonschema_forms.py
datasette_jsonschema_forms-0.0.3.dist-info/METADATA
datasette_jsonschema_forms-0.0.3.dist-info/WHEEL
datasette_jsonschema_forms-0.0.3.dist-info/entry_points.txt
datasette_jsonschema_forms-0.0.3.dist-info/top_level.txt
datasette_jsonschema_forms-0.0.3.dist-info/RECORD
