Metadata-Version: 2.4
Name: datasette-jsonschema-forms
Version: 0.0.3
Author: Alex Garcia
License-Expression: Apache-2.0
Project-URL: Homepage, https://github.com/datasette/datasette-jsonschema-forms
Project-URL: Changelog, https://github.com/datasette/datasette-jsonschema-forms/releases
Project-URL: Issues, https://github.com/datasette/datasette-jsonschema-forms/issues
Project-URL: CI, https://github.com/datasette/datasette-jsonschema-forms/actions
Classifier: Framework :: Datasette
Requires-Python: >=3.9
License-File: LICENSE
Requires-Dist: datasette>=1.0a19
Requires-Dist: sqlite-migrate>=0.1b0
Requires-Dist: sqlite-utils>=3.38
Requires-Dist: pydantic>=2
Provides-Extra: test
Requires-Dist: pytest; extra == "test"
Requires-Dist: pytest-asyncio; extra == "test"
Dynamic: license-file
